robots/__init__.py
robots/firefox_robot.py
longeni-1.1.dist-info/METADATA
longeni-1.1.dist-info/WHEEL
longeni-1.1.dist-info/top_level.txt
longeni-1.1.dist-info/RECORD
